tests
coverage_tools
