Metadata-Version: 1.1
Name: coverage-tools
Version: 0.0.4
Summary: Additional tools for Python coverage
Home-page: https://github.com/atodorov/coverage-tools
Author: Alexander Todorov
Author-email: atodorov@nospam.otb.bg
License: MIT
Keywords: code,coverage,testing
Platform: UNKNOWN
Classifier: Development Status :: 3 - Alpha
Classifier: Environment :: Console
Classifier: Intended Audience :: Developers
Classifier: License :: OSI Approved :: MIT License
Classifier: Operating System :: OS Independent
Classifier: Programming Language :: Python
Classifier: Topic :: Software Development :: Quality Assurance
Classifier: Topic :: Software Development :: Testing 
